{
  "timestamp": "2026-01-04T00:47:46Z",
  "run_id": "20685188864",
  "serial": "20251229",
  "epoch": 1766966400,
  "environment": {
    "timestamp": "2026-01-04T00:47:46Z",
    "os": {
      "name": "Ubuntu",
      "version": "24.04.3 LTS (Noble Numbat)",
      "kernel": "6.11.0-1018-azure",
      "arch": "x86_64"
    },
    "docker": "Docker version 28.0.4, build b8034c0",
    "qemu": "not installed",
    "git": {
      "version": "git version 2.52.0",
      "sha": "70bb6c0c957489a558668d3f77867edc563235ad",
      "branch": "main"
    },
    "github_actions": {
      "runner_os": "Linux",
      "runner_name": "GitHub Actions 1000004051",
      "runner_arch": "X64",
      "workflow": "Reproducible Debian Build",
      "run_id": "20685188864",
      "run_number": "48"
    }
  },
  "architectures": {
    "arm64": {
      "status": "success",
      "suites": {
        "bookworm": {
          "reproducible": true,
          "sha256": "6a54d94b371a7e12eb710210b87b63c19fde7c4300dfa9a580750b43d18480bc",
          "official_sha256": "6a54d94b371a7e12eb710210b87b63c19fde7c4300dfa9a580750b43d18480bc",
          "build_time_seconds": 142
        },
        "trixie": {
          "reproducible": true,
          "sha256": "6280203b4472adb6337450fd25674683fccb5421acba9856205db95b7ca37212",
          "official_sha256": "6280203b4472adb6337450fd25674683fccb5421acba9856205db95b7ca37212",
          "build_time_seconds": 150
        }
      }
    },
    "amd64": {
      "status": "success",
      "suites": {
        "bookworm": {
          "reproducible": true,
          "sha256": "504fb5a243d10a043d24ef0f35679ccfcc786d98bb3f7de9aa30a9d22d55a2fc",
          "official_sha256": "504fb5a243d10a043d24ef0f35679ccfcc786d98bb3f7de9aa30a9d22d55a2fc",
          "build_time_seconds": 102
        },
        "trixie": {
          "reproducible": true,
          "sha256": "a4d68e63e6da42f841ddebc90f41ac0ed1577e83bfd3e9be4b636f4ef81a4d47",
          "official_sha256": "a4d68e63e6da42f841ddebc90f41ac0ed1577e83bfd3e9be4b636f4ef81a4d47",
          "build_time_seconds": 86
        }
      }
    }
  }
}
